Metadata-Version: 2.1
Name: bsea
Version: 0.0.1
Summary: binary search
Author: Averyanova_Margarita
Author-email: margaritaaveryanova2004@gmail.com
